[{"username":"admin","img_url":"./header/admin.png","content":"asaaaaasss","time":"2022年8月31日 15:04:34","time_str":"1661929474927","list":[{"username":"admin","time_str":"1661929474927","time":"2022年8月31日 16:52:29","content":"a","img_url":"./header/admin.png"},{"username":"lzq","time_str":"1661929474927","time":"2022年8月31日 15:08:00","content":"啦啦啦啦啦","img_url":"./header/lzq.png"}]},{"username":"admin","img_url":"./header/admin.png","content":"aaa","time":"2022年8月31日 15:04:26","time_str":"1661929466186","list":[{"username":"admin","time_str":"1661929466186","time":"2022年8月31日 16:52:48","content":"sdsdasd","img_url":"./header/admin.png"},{"username":"lzq","time_str":"1661929466186","time":"2022年8月31日 15:08:43","content":"bbbbbbbbbb","img_url":"./header/lzq.png"},{"username":"lzq","time_str":"1661929466186","time":"2022年8月31日 15:07:50","content":"哈哈哈哈","img_url":"./header/lzq.png"}]},{"username":"admin","img_url":"./header/admin.png","content":"啦啦啦哈哈哈哈\n嘿嘿嘿","time":"2022年8月31日 14:56:41","time_str":"1661929001405","list":[{"username":"admin","index":"0","time":"2022年8月31日 15:04:21","content":"213123","img_url":"./header/admin.png"}]}]